climate_neutral/__init__.py
climate_neutral/version.py
climate_neutral-0.1.dev0.dist-info/METADATA
climate_neutral-0.1.dev0.dist-info/WHEEL
climate_neutral-0.1.dev0.dist-info/top_level.txt
climate_neutral-0.1.dev0.dist-info/RECORD
